{
  "openapi": "3.1.0",
  "info": {
    "title": "Darpan JSON-RPC API",
    "description": "Draft OpenAPI wrapper for Darpan's Moqui JSON-RPC service endpoint. Individual service contracts should be expanded from backend facade definitions as the API catalog matures.",
    "version": "draft"
  },
  "servers": [
    {
      "url": "http://localhost:8080",
      "description": "Local backend"
    }
  ],
  "security": [
    {
      "csrfToken": []
    }
  ],
  "paths": {
    "/rpc/json": {
      "post": {
        "summary": "Call a Darpan service",
        "description": "Submit a JSON-RPC request to a Darpan backend service. Authentication is session-cookie based and most calls require a valid CSRF token.",
        "operationId": "callDarpanJsonRpcService",
        "tags": [
          "JSON-RPC"
        ],
        "requestBody": {
          "description": "JSON-RPC request with a Moqui service name in `method` and service inputs in `params`.",
          "required": true,
          "content": {
            "application/json": {
              "schema": {
                "$ref": "#/components/schemas/JsonRpcRequest"
              },
              "examples": {
                "sessionInfo": {
                  "summary": "Get current session information",
                  "value": {
                    "jsonrpc": "2.0",
                    "id": 1,
                    "method": "facade.AuthFacadeServices.get#SessionInfo",
                    "params": {}
                  }
                }
              }
            }
          }
        },
        "responses": {
          "200": {
            "description": "JSON-RPC success or service-level error envelope.",
            "content": {
              "application/json": {
                "schema": {
                  "oneOf": [
                    {
                      "$ref": "#/components/schemas/JsonRpcSuccess"
                    },
                    {
                      "$ref": "#/components/schemas/JsonRpcError"
                    }
                  ]
                }
              }
            }
          },
          "401": {
            "description": "The session is missing, expired, or not authorized for the requested service."
          },
          "403": {
            "description": "The request is missing a required CSRF token or the user lacks permission."
          }
        }
      }
    }
  },
  "components": {
    "schemas": {
      "JsonRpcRequest": {
        "type": "object",
        "required": [
          "jsonrpc",
          "id",
          "method",
          "params"
        ],
        "properties": {
          "jsonrpc": {
            "type": "string",
            "const": "2.0"
          },
          "id": {
            "oneOf": [
              {
                "type": "string"
              },
              {
                "type": "integer"
              }
            ]
          },
          "method": {
            "type": "string",
            "description": "Moqui service name, for example `facade.AuthFacadeServices.get#SessionInfo`."
          },
          "params": {
            "type": "object",
            "additionalProperties": true
          }
        }
      },
      "JsonRpcSuccess": {
        "type": "object",
        "required": [
          "jsonrpc",
          "id",
          "result"
        ],
        "properties": {
          "jsonrpc": {
            "type": "string"
          },
          "id": {},
          "result": {
            "type": "object",
            "additionalProperties": true
          }
        }
      },
      "JsonRpcError": {
        "type": "object",
        "required": [
          "jsonrpc",
          "id",
          "error"
        ],
        "properties": {
          "jsonrpc": {
            "type": "string"
          },
          "id": {},
          "error": {
            "type": "object",
            "required": [
              "code",
              "message"
            ],
            "properties": {
              "code": {
                "type": "integer"
              },
              "message": {
                "type": "string"
              },
              "data": {
                "type": "object",
                "additionalProperties": true
              }
            }
          }
        }
      }
    },
    "securitySchemes": {
      "csrfToken": {
        "type": "apiKey",
        "in": "header",
        "name": "X-CSRF-Token",
        "description": "CSRF token returned by the backend login/session flow."
      }
    }
  }
}
